streamlit_framework_multilit-0.7.7.dist-info/licenses/LICENSE
streamlit_plugins/framework/multilit/__init__.py
streamlit_plugins/framework/multilit/app_wrapper.py
streamlit_plugins/framework/multilit/loading_engine.py
streamlit_plugins/framework/multilit/multilit.py
streamlit_framework_multilit-0.7.7.dist-info/METADATA
streamlit_framework_multilit-0.7.7.dist-info/WHEEL
streamlit_framework_multilit-0.7.7.dist-info/top_level.txt
streamlit_framework_multilit-0.7.7.dist-info/RECORD
